kedro_databricks/__init__.py
kedro_databricks/constants.py
kedro_databricks/plugin.py
kedro_databricks/commands/__init__.py
kedro_databricks/commands/bundle.py
kedro_databricks/commands/deploy.py
kedro_databricks/commands/destroy.py
kedro_databricks/commands/init.py
kedro_databricks/commands/run.py
kedro_databricks/commands/version.py
kedro_databricks/templates/databricks.yml.tmpl
kedro_databricks/templates/databricks_run.py
kedro_databricks/templates/databricks_template_schema.json
kedro_databricks/utilities/__init__.py
kedro_databricks/utilities/common.py
kedro_databricks/utilities/databricks_cli.py
kedro_databricks/utilities/logger.py
kedro_databricks/utilities/plugin.py
kedro_databricks/utilities/resolver_generics.py
kedro_databricks/utilities/resource_generator/__init__.py
kedro_databricks/utilities/resource_generator/abstract_resource_generator.py
kedro_databricks/utilities/resource_generator/node_resource_generator.py
kedro_databricks/utilities/resource_generator/pipeline_resource_generator.py
kedro_databricks/utilities/resource_overrider/__init__.py
kedro_databricks/utilities/resource_overrider/abstract_resource_overrider.py
kedro_databricks/utilities/resource_overrider/default_resource_overrider.py
kedro_databricks/utilities/resource_overrider/jobs_resource_overrider.py
kedro_databricks-0.14.1.dist-info/METADATA
kedro_databricks-0.14.1.dist-info/WHEEL
kedro_databricks-0.14.1.dist-info/entry_points.txt
kedro_databricks-0.14.1.dist-info/licenses/LICENSE
kedro_databricks-0.14.1.dist-info/RECORD
