Metadata-Version: 2.4
Name: kedro-databricks
Version: 0.14.1
Summary: A plugin to run Kedro pipelines on Databricks.
Project-URL: Homepage, https://github.com/jenspederm/kedro-databricks
Project-URL: Issues, https://github.com/jenspederm/kedro-databricks/issues
Author-email: Jens Peder Meldgaard <jenspederm@gmail.com>
License-File: LICENSE
Requires-Python: >=3.10
Requires-Dist: databricks-sdk>=0.36.0
Requires-Dist: kedro>=0.19.8
Requires-Dist: packaging>=21.2
Requires-Dist: python-dotenv>=1.0.1
Requires-Dist: tomlkit>=0.13.0
